yasumi-0.3.2.dist-info/METADATA
yasumi-0.3.2.dist-info/WHEEL
yasumi-0.3.2.dist-info/licenses/LICENSE
yasumi/__init__.py
yasumi/__init__.pyi
yasumi/py.typed
yasumi/yasumi.cp39-win_amd64.pyd
yasumi-0.3.2.dist-info/RECORD
